odoo/addons/sale_commission_salesman/README.rst
odoo/addons/sale_commission_salesman/__init__.py
odoo/addons/sale_commission_salesman/__manifest__.py
odoo/addons/sale_commission_salesman/i18n/ca.po
odoo/addons/sale_commission_salesman/i18n/es.po
odoo/addons/sale_commission_salesman/i18n/es_AR.po
odoo/addons/sale_commission_salesman/i18n/it.po
odoo/addons/sale_commission_salesman/i18n/pt_BR.po
odoo/addons/sale_commission_salesman/i18n/sale_commission_salesman.pot
odoo/addons/sale_commission_salesman/i18n/tr.po
odoo/addons/sale_commission_salesman/models/__init__.py
odoo/addons/sale_commission_salesman/models/account_move.py
odoo/addons/sale_commission_salesman/models/res_partner.py
odoo/addons/sale_commission_salesman/models/sale_order.py
odoo/addons/sale_commission_salesman/readme/CONFIGURE.md
odoo/addons/sale_commission_salesman/readme/CONTRIBUTORS.md
odoo/addons/sale_commission_salesman/readme/CREDITS.md
odoo/addons/sale_commission_salesman/readme/DESCRIPTION.md
odoo/addons/sale_commission_salesman/readme/ROADMAP.md
odoo/addons/sale_commission_salesman/readme/USAGE.md
odoo/addons/sale_commission_salesman/static/description/icon.png
odoo/addons/sale_commission_salesman/static/description/icon.svg
odoo/addons/sale_commission_salesman/static/description/index.html
odoo/addons/sale_commission_salesman/tests/__init__.py
odoo/addons/sale_commission_salesman/tests/test_sale_commission_salesman.py
odoo/addons/sale_commission_salesman/views/res_partner_views.xml
odoo_addon_sale_commission_salesman-18.0.1.0.0.2.dist-info/METADATA
odoo_addon_sale_commission_salesman-18.0.1.0.0.2.dist-info/WHEEL
odoo_addon_sale_commission_salesman-18.0.1.0.0.2.dist-info/top_level.txt
odoo_addon_sale_commission_salesman-18.0.1.0.0.2.dist-info/RECORD
