Metadata-Version: 2.1
Name: odoo-addon-sale_commission_salesman
Version: 18.0.1.0.0.2
Requires-Python: >=3.10
Requires-Dist: odoo-addon-sale_commission_oca==18.0.*
Requires-Dist: odoo==18.0.*
Summary: Sales commissions from salesman
Home-page: https://github.com/OCA/commission
License: AGPL-3
Author: Tecnativa, Odoo Community Association (OCA)
Author-email: support@odoo-community.org
Classifier: Programming Language :: Python
Classifier: Framework :: Odoo
Classifier: Framework :: Odoo :: 18.0
Classifier: License :: OSI Approved :: GNU Affero General Public License v3
